<?xml version='1.0' encoding='UTF-8'?>
<annotation>
	<folder>news_imagens</folder>
	<filename>gettyimages-75375063-1024x1024_hflipped_flipped.jpg</filename>
	<path>C:\Users\mathe\Desktop\Orange\TensorFlow_v2\news_imagens\gettyimages-75375063-1024x1024_hflipped_flipped.jpg</path>
	<source>
		<database>Unknown</database>
	</source>
	<size>
		<width>894</width>
		<height>1024</height>
		<depth>3</depth>
	</size>
	<segmented>0</segmented>
	<object>
		<name>thumbsdown</name>
		<pose>Unspecified</pose>
		<truncated>0</truncated>
		<difficult>0</difficult>
		<bndbox>
			<xmin>603</xmin>
			<ymin>602</ymin>
			<xmax>747</xmax>
			<ymax>924</ymax>
		</bndbox>
	</object>
	<object>
		<name>thumbsdown</name>
		<pose>Unspecified</pose>
		<truncated>0</truncated>
		<difficult>0</difficult>
		<bndbox>
			<xmin>567</xmin>
			<ymin>208</ymin>
			<xmax>710</xmax>
			<ymax>510</ymax>
		</bndbox>
	</object>
</annotation>