<?xml version='1.0' encoding='UTF-8'?>
<annotation>
	<folder>news_imagens</folder>
	<filename>gettyimages-149317075-2048x2048_flipped.jpg</filename>
	<path>C:\Users\mathe\Desktop\Orange\TensorFlow_v2\news_imagens\gettyimages-149317075-2048x2048_flipped.jpg</path>
	<source>
		<database>Unknown</database>
	</source>
	<size>
		<width>2048</width>
		<height>1366</height>
		<depth>3</depth>
	</size>
	<segmented>0</segmented>
	<object>
		<name>thumbsup</name>
		<pose>Unspecified</pose>
		<truncated>0</truncated>
		<difficult>0</difficult>
		<bndbox>
			<xmin>1371</xmin>
			<ymin>448</ymin>
			<xmax>1746</xmax>
			<ymax>974</ymax>
		</bndbox>
	</object>
	<object>
		<name>thumbsup</name>
		<pose>Unspecified</pose>
		<truncated>0</truncated>
		<difficult>0</difficult>
		<bndbox>
			<xmin>229</xmin>
			<ymin>408</ymin>
			<xmax>535</xmax>
			<ymax>915</ymax>
		</bndbox>
	</object>
</annotation>