<?xml version='1.0' encoding='UTF-8'?>
<annotation>
	<folder>images</folder>
	<filename>istockphoto-920486436-1024x1024_hflipped.jpg</filename>
	<path>/home/vkhg7500/Documents/images/istockphoto-920486436-1024x1024_hflipped.jpg</path>
	<source>
		<database>Unknown</database>
	</source>
	<size>
		<width>1024</width>
		<height>687</height>
		<depth>3</depth>
	</size>
	<segmented>0</segmented>
	<object>
		<name>thumbsdown</name>
		<pose>Unspecified</pose>
		<truncated>0</truncated>
		<difficult>0</difficult>
		<bndbox>
			<xmin>615</xmin>
			<ymin>325</ymin>
			<xmax>731</xmax>
			<ymax>593</ymax>
		</bndbox>
	</object>
</annotation>