<?xml version='1.0' encoding='UTF-8'?>
<annotation>
	<folder>images</folder>
	<filename>istockphoto-943109686-2048x2048_flipped.jpg</filename>
	<path>/home/vkhg7500/Documents/images/istockphoto-943109686-2048x2048_flipped.jpg</path>
	<source>
		<database>Unknown</database>
	</source>
	<size>
		<width>2048</width>
		<height>1367</height>
		<depth>3</depth>
	</size>
	<segmented>0</segmented>
	<object>
		<name>thumbsup</name>
		<pose>Unspecified</pose>
		<truncated>0</truncated>
		<difficult>0</difficult>
		<bndbox>
			<xmin>1326</xmin>
			<ymin>520</ymin>
			<xmax>1576</xmax>
			<ymax>886</ymax>
		</bndbox>
	</object>
	<object>
		<name>thumbsup</name>
		<pose>Unspecified</pose>
		<truncated>0</truncated>
		<difficult>0</difficult>
		<bndbox>
			<xmin>568</xmin>
			<ymin>521</ymin>
			<xmax>786</xmax>
			<ymax>884</ymax>
		</bndbox>
	</object>
</annotation>